flask_socketio_lit_html/webcomponent_base.py
flask_socketio_lit_html/webcomponent_templates/webcomponent_base.js
flask_socketio_lit_html/webcomponents_static/element.js
flask_socketio_lit_html/webcomponents_static/socketio-4.1.2.js
flask_socketio_lit_html-0.1.10.dist-info/LICENSE.txt
flask_socketio_lit_html-0.1.10.dist-info/WHEEL
flask_socketio_lit_html-0.1.10.dist-info/METADATA
flask_socketio_lit_html-0.1.10.dist-info/RECORD
